commonpy/__init__.py
commonpy/data_structures.py
commonpy/data_utils.py
commonpy/exceptions.py
commonpy/file_utils.py
commonpy/interrupt.py
commonpy/module_utils.py
commonpy/network_utils.py
commonpy/string_utils.py
commonpy/system_utils.py
commonpy-1.13.0.dist-info/LICENSE
commonpy-1.13.0.dist-info/METADATA
commonpy-1.13.0.dist-info/WHEEL
commonpy-1.13.0.dist-info/top_level.txt
commonpy-1.13.0.dist-info/RECORD
