Metadata-Version: 2.1
Name: commonpy
Version: 1.13.0
Summary: Assortment of Python helper functions and utility classes
Home-page: https://github.com/caltechlibrary/commonpy
Author: Michael Hucka
Author-email: mhucka@caltech.edu
License: BSD 3-clause
Project-URL: Source Code, https://github.com/caltechlibrary/commonpy
Project-URL: Bug Tracker, https://github.com/caltechlibrary/commonpy/issues
Keywords: Python,utilities
Classifier: Development Status :: 5 - Production/Stable
Classifier: License :: OSI Approved :: BSD License
Classifier: Intended Audience :: Science/Research
Classifier: Operating System :: MacOS :: MacOS X
Classifier: Operating System :: Microsoft :: Windows
Classifier: Operating System :: POSIX
Classifier: Operating System :: POSIX :: Linux
Classifier: Operating System :: Unix
Classifier: Programming Language :: Python
Classifier: Programming Language :: Python :: 3.6
Requires-Python: >=3.6
License-File: LICENSE
